Workbook

Sheet CONSTANTS
A1: Risk Free Rate | B1: 0.04
A2: Corporate Tax Rate | B2: 0.3
A3: Market Risk Premium | B3: 0.08
A4: Equipment Depreciation Rate | B4: 0.125
A5: Warehouse and Plan Depreciation Rate | B5: 0.04
A6: Monthly Rent | B6: 2500
A9: NWC
A10: Inventory | B10: 0.1 | C10: of COGs
A11: Receivables | B11: 0.2 | C11: of Sales
A12: Payables | B12: 0.05 | C12: of COGs
A14: Comparable Beta | B14: 1.5
A15: Comparable D/E Ratio | B15: 0.5
A17: Unlevered Beta | B17: =B14/(1+(1-B2)*0.5) -> 1.1111111
A18: Estimated WACC using CAPM | B18: =B5+(B17*B3) -> 0.12888889

Sheet 2025 Expenses
B1: Water | C1: Winter | D1: Shared
A2: Cost Per Unit Sold | B2: 280 | C2: 150
A3: Admin and General Expenses | D3: 500000
A4: Marketing and Sales | D4: 250000
A5: Research and Development | D5: 750000
A6: Other operational costs | B6: 15000 | C6: 50000 | D6: 10000
A7: Interest | D7: 20000

Sheet Question 1
A1: Earnings Forecast
B3: 2025 | C3: 2026 | D3: 2027 | E3: 2028 | F3: 2029 | G3: 2030 | H3: 2031
A4: Sales | C4: =SUM(Wrangling!C22,Wrangling!J22) -> 2892750 | D4: =SUM(Wrangling!D22,Wrangling!K22) -> 4163040 | E4: =SUM(Wrangling!E22,Wrangling!L22) -> 5666574.4 | F4: =SUM(Wrangling!F22,Wrangling!M22) -> 6299361.1 | G4: =SUM(Wrangling!G22,Wrangling!N22) -> 7003698.8
A5: COGS | C5: =SUM(Wrangling!C30,Wrangling!J30) -> -2191385 | D5: =SUM(Wrangling!D30,Wrangling!K30) -> -3043799.8 | E5: =SUM(Wrangling!E30,Wrangling!L30) -> -4005471 | F5: =SUM(Wrangling!F30,Wrangling!M30) -> -4302860.7 | G5: =SUM(Wrangling!G30,Wrangling!N30) -> -4622904.7
A6: Gross Profit | C6: =C4+C5 -> 701365 | D6: =D4+D5 -> 1119240.2 | E6: =E4+E5 -> 1661103.4 | F6: =F4+F5 -> 1996500.4 | G6: =G4+G5 -> 2380794
A7: Selling, General, Administrative | C7: =Wrangling!R26+Wrangling!R27+Wrangling!C29+Wrangling!J29+Wrangling!R29 -> -858000 | D7: =Wrangling!S26+Wrangling!S27+Wrangling!D29+Wrangling!K29+Wrangling!S29 -> -892320 | E7: =Wrangling!T26+Wrangling!T27+Wrangling!E29+Wrangling!L29+Wrangling!T29 -> -928012.8 | F7: =Wrangling!U26+Wrangling!U27+Wrangling!F29+Wrangling!M29+Wrangling!U29 -> -965133.31 | G7: =Wrangling!V26+Wrangling!V27+Wrangling!G29+Wrangling!N29+Wrangling!V29 -> -1003738.6
A8: Research and Devlopment | B8: =Wrangling!Q28 -> -750000
A9: Depreciation | B9: =Wrangling!Q33+Wrangling!Q31 -> 0 | C9: =Wrangling!R33+Wrangling!R31 -> -67500 | D9: =Wrangling!S33+Wrangling!S31 -> -105000 | E9: =Wrangling!T33+Wrangling!T31 -> -142500 | F9: =Wrangling!U33+Wrangling!U31 -> -180000 | G9: =Wrangling!V33+Wrangling!V31 -> -217500
A10: Opportunity Cost for Rent | C10: =Wrangling!R36 -> -30000 | D10: =Wrangling!S36 -> -30000 | E10: =Wrangling!T36 -> -30000 | F10: =Wrangling!U36 -> -30000 | G10: =Wrangling!V36 -> -30000
A11: EBIT | B11: =SUM(B6:B10) -> -750000 | C11: =SUM(C6:C10) -> -254135 | D11: =SUM(D6:D10) -> 91920.238 | E11: =SUM(E6:E10) -> 560590.56 | F11: =SUM(F6:F10) -> 821367.13 | G11: =SUM(G6:G10) -> 1129555.4
A12: Corporate Tax | B12: =-(B11)*CONSTANTS!$B$2 -> 225000 | C12: =-(C11)*CONSTANTS!$B$2 -> 76240.5 | D12: =-(D11)*CONSTANTS!$B$2 -> -27576.071 | E12: =-(E11)*CONSTANTS!$B$2 -> -168177.17 | F12: =-(F11)*CONSTANTS!$B$2 -> -246410.14 | G12: =-(G11)*CONSTANTS!$B$2 -> -338866.61
A13: Unlevered Net Income | B13: =SUM(B11:B12) -> -525000 | C13: =SUM(C11:C12) -> -177894.5 | D13: =SUM(D11:D12) -> 64344.166 | E13: =SUM(E11:E12) -> 392413.39 | F13: =SUM(F11:F12) -> 574956.99 | G13: =SUM(G11:G12) -> 790688.77
A14: Free Cash Flow
A15: Depreciation | B15: =B9*(-1) -> 0 | C15: =C9*(-1) -> 67500 | D15: =D9*(-1) -> 105000 | E15: =E9*(-1) -> 142500 | F15: =F9*(-1) -> 180000 | G15: =G9*(-1) -> 217500
A16: CapEx | B16: =Wrangling!Q32+Wrangling!Q35 -> -1050000 | C16: =Wrangling!R32+Wrangling!R35 -> -300000 | D16: =Wrangling!S32+Wrangling!S35 -> -300000 | E16: =Wrangling!T32+Wrangling!T35 -> -300000 | F16: =Wrangling!U32+Wrangling!U35 -> -300000 | G16: =Wrangling!V32+Wrangling!V35 -> -300000
A17: Change in NWC | B17: 0 | C17: =(Wrangling!C39+Wrangling!J39) -> 688119.25 | D17: =(Wrangling!D39+Wrangling!K39) -> 296678.74 | E17: =(Wrangling!E39+Wrangling!L39) -> 348790.44 | F17: =(Wrangling!F39+Wrangling!M39) -> 141426.84 | G17: =(Wrangling!G39+Wrangling!N39) -> 156869.73
A18: Salvage and NWC Recovery | H18: =Wrangling!W38 -> 3749385
A19: Free Cash Flow | B19: =SUM(B13,B15:B18) -> -1575000 | C19: =C13+C15+C16-C17 -> -1098513.8 | D19: =D13+D15+D16-D17 -> -427334.57 | E19: =E13+E15+E16-E17 -> -113877.05 | F19: =F13+F15+F16-F17 -> 313530.15 | G19: =G13+G15+G16-G17 -> 551319.04 | H19: =SUM(H13,H15:H18) -> 3749385
A20: Net Present Value | B20: Estimated WACC: | C20: =CONSTANTS!B18 -> 0.12888889
A21: FCF PV | B21: =B19/((1+$C$20)^(B3-2025)) -> -1575000 | C21: =C19/((1+$C$20)^(C3-2025)) -> -973092.89 | D21: =D19/((1+$C$20)^(D3-2025)) -> -335324.77 | E21: =E19/((1+$C$20)^(E3-2025)) -> -79155.774 | F21: =F19/((1+$C$20)^(F3-2025)) -> 193052.09 | G21: =G19/((1+$C$20)^(G3-2025)) -> 300709.4 | H21: =H19/((1+$C$20)^(H3-2025)) -> 1811560.5
A22: NPV | B22: =SUM(B21:H21) -> -657251.43
A23: IRR | B23: =IRR(B19:H19) -> 0.074298611
A24: Payback
A25: Cumilative | B25: =B19 -> -1575000 | C25: =SUM(B19:C19) -> -2673513.8 | D25: =SUM(B19:D19) -> -3100848.3 | E25: =SUM(B19:E19) -> -3214725.4 | F25: =SUM(B19:F19) -> -2901195.2 | G25: =SUM(B19:G19) -> -2349876.2 | H25: =SUM(B19:H19) -> 1399508.8
H26: =ABS(G25/H19) -> 0.62673643
G27: Approx | H27: =5+H26 -> 5.6267364 | I27: years

Sheet Question 2
F1: Assets | H1: Liability and Stockholder's Equity
F2: Cash | G2: =I7-SUM(G3:G6) -> 864849.19 | H2: Payables | I2: =SUM(Wrangling!G43,Wrangling!N43) -> 231145.24
F3: Inventory | G3: =SUM(Wrangling!G41,Wrangling!N41) -> 462290.47 | H3: Retained Earnings | I3: =SUM('Question 1'!B13:G13) -> 1119508.8
F4: Receivables | G4: =SUM(Wrangling!G42,Wrangling!N42) -> 1400739.8 | H4: Injected Capital | I4: =ABS('Question 1'!E25) -> 3214725.4
F5: Warehouse and Plant | G5: =ABS(Wrangling!Q35-SUM(Wrangling!R31:V31)) -> 600000 | H5: Net Equity | I5: =SUM(I3:I4) -> 4334234.2
F6: Equipment | G6: =ABS(SUM(Wrangling!Q32:V32)-SUM(Wrangling!R33:V33)) -> 1237500
F7: Total Assets | G7: =SUM(G2:G6) -> 4565379.4 | H7: Total Liabilities and Stockholders Equity | I7: =SUM(I5,I2) -> 4565379.4

Sheet Question 3 + 4
A1: QUESTION 3
A2: Sale Price of Winter Sports | C2: ='Question 1'!$B$22 -> -657251.43 | K2: Sale Price of Water Sports | M2: ='Question 1'!$B$22 -> -657251.43 | S2: CPU of Winter Sports | U2: ='Question 1'!$B$22 -> -657251.43 | AA2: CPU of Water Sports | AC2: ='Question 1'!$B$22 -> -657251.43 | AH2: Admin and General Expenses | AJ2: ='Question 1'!$B$22 -> -657251.43
B3: 100 | C3: -2726557.3 | L3: 175 | M3: -4501906.8 | T3: -75 | U3: 794711.65 | AB3: -140 | AC3: 2225513.2 | AI3: -250000 | AJ3: 31514.036
B4: 125 | C4: -2209230.9 | L4: 200 | M4: -3952670.3 | T4: -100 | U4: 310723.96 | AB4: -160 | AC4: 1813689.7 | AI4: -300000 | AJ4: -106239.06
B5: 150 | C5: -1691904.4 | L5: 225 | M5: -3403433.8 | T5: -125 | U5: -173263.73 | AB5: -180 | AC5: 1401866.2 | AI5: -350000 | AJ5: -243992.15
B6: 175 | C6: -1174577.9 | L6: 250 | M6: -2854197.3 | T6: -150 | U6: -657251.43 | AB6: -200 | AC6: 990042.64 | AI6: -400000 | AJ6: -381745.24
B7: 200 | C7: -657251.43 | L7: 275 | M7: -2304960.9 | T7: -175 | U7: -1141239.1 | AB7: -220 | AC7: 578219.12 | AI7: -450000 | AJ7: -519498.33
B8: 225 | C8: -139924.95 | L8: 300 | M8: -1755724.4 | T8: -200 | U8: -1625226.8 | AB8: -240 | AC8: 166395.6 | AI8: -500000 | AJ8: -657251.43
B9: 250 | C9: 377401.53 | L9: 325 | M9: -1206487.9 | T9: -225 | U9: -2109214.5 | AB9: -260 | AC9: -245427.91 | AI9: -550000 | AJ9: -795004.52
B10: 275 | C10: 894728 | L10: 350 | M10: -657251.43 | T10: -250 | U10: -2593202.2 | AB10: -280 | AC10: -657251.43 | AI10: -600000 | AJ10: -932757.61
B11: 300 | C11: 1412054.5 | L11: 375 | M11: -108014.95 | T11: -275 | U11: -3077189.9 | AB11: -300 | AC11: -1069074.9 | AI11: -650000 | AJ11: -1070510.7
B12: 325 | C12: 1929381 | L12: 400 | M12: 441221.53 | T12: -300 | U12: -3561177.6 | AB12: -320 | AC12: -1480898.5 | AI12: -700000 | AJ12: -1208263.8
B13: 350 | C13: 2446707.4 | L13: 425 | M13: 990458.01 | AB13: -340 | AC13: -1892722 | AI13: -750000 | AJ13: -1346016.9
B14: 375 | C14: 2964033.9 | L14: 450 | M14: 1539694.5 | AB14: -360 | AC14: -2304545.5 | AI14: -800000 | AJ14: -1483770
B15: 400 | C15: 3481360.4 | L15: 475 | M15: 2088931 | AB15: -380 | AC15: -2716369 | AI15: -850000 | AJ15: -1621523.1
L16: 500 | M16: 2638167.4 | AB16: -400 | AC16: -3128192.5 | AI16: -900000 | AJ16: -1759276.2
L17: 525 | M17: 3187403.9 | AB17: -420 | AC17: -3540016 | AI17: -950000 | AJ17: -1897029.3
L18: 550 | M18: 3736640.4 | AB18: -440 | AC18: -3951839.6 | AI18: -1000000 | AJ18: -2034782.4
L19: 575 | M19: 4285876.9 | AB19: -460 | AC19: -4363663.1
L20: 600 | M20: 4835113.4 | AB20: -480 | AC20: -4775486.6
L21: 625 | M21: 5384349.8 | AB21: -500 | AC21: -5187310.1
L22: 650 | M22: 5933586.3 | AB22: -520 | AC22: -5599133.6
L23: 675 | M23: 6482822.8 | AB23: -540 | AC23: -6010957.1
L24: 700 | M24: 7032059.3 | AB24: -560 | AC24: -6422780.7
A50: QUESTION 4 | B50: Scenario | C50: Pessimistic | D50: Optimistic | E50: STANDARD
A51: Default Values | B51: 3
A52: =CHOOSE($B$51,C52,D52,E52) -> 350 | B52: Initial Sale Price of water sports | C52: 340 | D52: 365 | E52: 350
A53: =CHOOSE($B$51,C53,D53,E53) -> 200 | B53: Initial Sale Price of winter sports | C53: 245 | D53: 275 | E53: 200
A54: =CHOOSE($B$51,C54,D54,E54) -> -280 | B54: Initial Cost per Unit of water sports | C54: -295 | D54: -275 | E54: -280
A55: =CHOOSE($B$51,C55,D55,E55) -> -150 | B55: Initial Cost per Unit of winter sports | C55: -165 | D55: -145 | E55: -150
A56: =CHOOSE($B$51,C56,D56,E56) -> -500000 | B56: Initial admin and general expenses | C56: -600000 | D56: -500000 | E56: -500000
A57: =CHOOSE($B$51,C57,D57,E57) -> 0.075 | B57: Sales growth rate for 2029 and 2030 (Winter) | C57: 0.075 | D57: 0.1 | E57: 0.075
A58: =CHOOSE($B$51,C58,D58,E58) -> 0.05 | B58: Sales growth rate for 2029 and 2030 (Water) | C58: 0.05 | D58: 0.1 | E58: 0.05
A59: =CHOOSE($B$51,C59,D59,E59) -> -250000 | B59: Marketing and Sales | C59: -250000 | D59: -300000 | E59: -250000
A62: NPV | B62: ='Question 1'!$B$22 -> -657251.43 | C62: -820524.8 | D62: 1417306.9 | E62: -657251.43
A63: IRR | B63: ='Question 1'!B23 -> 0.074298611 | C63: 0.062958688 | D63: 0.24541023 | E63: 0.074298611

Sheet Wrangling
A1: Forecasted Sales | E1: Water | L1: Winter | T1: Shared
B2: 2025 | C2: 2026 | D2: 2027 | E2: 2028 | F2: 2029 | G2: 2030 | H2: 2031 | I2: 2025 | J2: 2026 | K2: 2027 | L2: 2028 | M2: 2029 | N2: 2030 | O2: 2031 | Q2: 2025 | R2: 2026 | S2: 2027 | T2: 2028 | U2: 2029 | V2: 2030 | W2: 2031
A3: France | C3: 200 | D3: 350 | E3: 500 | F3: =E3*(1+'Question 3 + 4'!$A$58) -> 525 | G3: =F3*(1+'Question 3 + 4'!$A$58) -> 551.25 | J3: 700 | K3: 850 | L3: 1100 | M3: =L3*(1+'Question 3 + 4'!$A$57) -> 1182.5 | N3: =M3*(1+'Question 3 + 4'!$A$57) -> 1271.1875
A4: UK | C4: 2000 | D4: 2500 | E4: 3000 | F4: =E4*(1+'Question 3 + 4'!$A$58) -> 3150 | G4: =F4*(1+'Question 3 + 4'!$A$58) -> 3307.5 | J4: 1500 | K4: 3000 | L4: 3500 | M4: =L4*(1+'Question 3 + 4'!$A$57) -> 3762.5 | N4: =M4*(1+'Question 3 + 4'!$A$57) -> 4044.6875
A5: Italy | C5: 1500 | D5: 2000 | E5: 2000 | F5: =E5*(1+'Question 3 + 4'!$A$58) -> 2100 | G5: =F5*(1+'Question 3 + 4'!$A$58) -> 2205 | J5: 1000 | K5: 1200 | L5: 1350 | M5: =L5*(1+'Question 3 + 4'!$A$57) -> 1451.25 | N5: =M5*(1+'Question 3 + 4'!$A$57) -> 1560.0938
A6: Spain | C6: 1500 | D6: 2000 | E6: 3500 | F6: =E6*(1+'Question 3 + 4'!$A$58) -> 3675 | G6: =F6*(1+'Question 3 + 4'!$A$58) -> 3858.75 | J6: 1250 | K6: 1500 | L6: 2500 | M6: =L6*(1+'Question 3 + 4'!$A$57) -> 2687.5 | N6: =M6*(1+'Question 3 + 4'!$A$57) -> 2889.0625
A7: Portugal | C7: 100 | D7: 150 | E7: 100 | F7: =E7*(1+'Question 3 + 4'!$A$58) -> 105 | G7: =F7*(1+'Question 3 + 4'!$A$58) -> 110.25 | J7: 50 | K7: 80 | L7: 100 | M7: =L7*(1+'Question 3 + 4'!$A$57) -> 107.5 | N7: =M7*(1+'Question 3 + 4'!$A$57) -> 115.5625
A14: Forecasted Unit Selling Price | B14: ='Question 3 + 4'!A52 -> 350 | C14: =B14*1.05 -> 367.5 | D14: =C14*1.05 -> 385.875 | E14: =D14*1.05 -> 405.16875 | F14: =E14*1.05 -> 425.42719 | G14: =F14*1.05 -> 446.69855 | I14: ='Question 3 + 4'!A53 -> 200 | J14: =I14*1.05 -> 210 | K14: =J14*1.05 -> 220.5 | L14: =K14*1.05 -> 231.525 | M14: =L14*1.05 -> 243.10125 | N14: =M14*1.05 -> 255.25631
A16: Forecasted Sales (GBP)
A17: France | C17: =C3*C$14 -> 73500 | D17: =D3*D$14 -> 135056.25 | E17: =E3*E$14 -> 202584.38 | F17: =F3*F$14 -> 223349.27 | G17: =G3*G$14 -> 246242.57 | J17: =J3*J$14 -> 147000 | K17: =K3*K$14 -> 187425 | L17: =L3*L$14 -> 254677.5 | M17: =M3*M$14 -> 287467.23 | N17: =N3*N$14 -> 324478.63
A18: UK | C18: =C4*C$14 -> 735000 | D18: =D4*D$14 -> 964687.5 | E18: =E4*E$14 -> 1215506.3 | F18: =F4*F$14 -> 1340095.6 | G18: =G4*G$14 -> 1477455.4 | J18: =J4*J$14 -> 315000 | K18: =K4*K$14 -> 661500 | L18: =L4*L$14 -> 810337.5 | M18: =M4*M$14 -> 914668.45 | N18: =N4*N$14 -> 1032432
A19: Italy | C19: =C5*C$14 -> 551250 | D19: =D5*D$14 -> 771750 | E19: =E5*E$14 -> 810337.5 | F19: =F5*F$14 -> 893397.09 | G19: =G5*G$14 -> 984970.3 | J19: =J5*J$14 -> 210000 | K19: =K5*K$14 -> 264600 | L19: =L5*L$14 -> 312558.75 | M19: =M5*M$14 -> 352800.69 | N19: =N5*N$14 -> 398223.78
A20: Spain | C20: =C6*C$14 -> 551250 | D20: =D6*D$14 -> 771750 | E20: =E6*E$14 -> 1418090.6 | F20: =F6*F$14 -> 1563444.9 | G20: =G6*G$14 -> 1723698 | J20: =J6*J$14 -> 262500 | K20: =K6*K$14 -> 330750 | L20: =L6*L$14 -> 578812.5 | M20: =M6*M$14 -> 653334.61 | N20: =N6*N$14 -> 737451.44
A21: Portugal | C21: =C7*C$14 -> 36750 | D21: =D7*D$14 -> 57881.25 | E21: =E7*E$14 -> 40516.875 | F21: =F7*F$14 -> 44669.855 | G21: =G7*G$14 -> 49248.515 | J21: =J7*J$14 -> 10500 | K21: =K7*K$14 -> 17640 | L21: =L7*L$14 -> 23152.5 | M21: =M7*M$14 -> 26133.384 | N21: =N7*N$14 -> 29498.058
A22: TOTAL | C22: =SUM(C17:C21) -> 1947750 | D22: =SUM(D17:D21) -> 2701125 | E22: =SUM(E17:E21) -> 3687035.6 | F22: =SUM(F17:F21) -> 4064956.8 | G22: =SUM(G17:G21) -> 4481614.8 | J22: =SUM(J17:J21) -> 945000 | K22: =SUM(K17:K21) -> 1461915 | L22: =SUM(L17:L21) -> 1979538.8 | M22: =SUM(M17:M21) -> 2234404.4 | N22: =SUM(N17:N21) -> 2522083.9
A24: Forecasted Expenses
A25: Cost per Unit Sold | B25: ='Question 3 + 4'!A54 -> -280 | C25: =B25*1.015 -> -284.2 | D25: =C25*1.015 -> -288.463 | E25: =D25*1.015 -> -292.78994 | F25: =E25*1.015 -> -297.18179 | G25: =F25*1.015 -> -301.63952 | I25: ='Question 3 + 4'!A55 -> -150 | J25: =I25*1.015 -> -152.25 | K25: =J25*1.015 -> -154.53375 | L25: =K25*1.015 -> -156.85176 | M25: =L25*1.015 -> -159.20453 | N25: =M25*1.015 -> -161.5926
P26: Admin and General Expenses | Q26: ='Question 3 + 4'!A56 -> -500000 | R26: =Q26*1.04 -> -520000 | S26: =R26*1.04 -> -540800 | T26: =S26*1.04 -> -562432 | U26: =T26*1.04 -> -584929.28 | V26: =U26*1.04 -> -608326.45
P27: Marketing and Sales | Q27: ='Question 3 + 4'!A59 -> -250000 | R27: =Q27*1.04 -> -260000 | S27: =R27*1.04 -> -270400 | T27: =S27*1.04 -> -281216 | U27: =T27*1.04 -> -292464.64 | V27: =U27*1.04 -> -304163.23
P28: Research and Development | Q28: -750000
A29: Other operational costs | C29: =-15000*1.04 -> -15600 | D29: =C29*1.04 -> -16224 | E29: =D29*1.04 -> -16872.96 | F29: =E29*1.04 -> -17547.878 | G29: =F29*1.04 -> -18249.794 | J29: =-'2025 Expenses'!$C$6*1.04 -> -52000 | K29: =J29*1.04 -> -54080 | L29: =K29*1.04 -> -56243.2 | M29: =L29*1.04 -> -58492.928 | N29: =M29*1.04 -> -60832.645 | Q29: -10000 | R29: =Q29*1.04 -> -10400 | S29: =R29*1.04 -> -10816 | T29: =S29*1.04 -> -11248.64 | U29: =T29*1.04 -> -11698.586 | V29: =U29*1.04 -> -12166.529
A30: COGS | C30: =C$25*SUM(C3:C7) -> -1506260 | D30: =D$25*SUM(D3:D7) -> -2019241 | E30: =E$25*SUM(E3:E7) -> -2664388.5 | F30: =F$25*SUM(F3:F7) -> -2839572 | G30: =G$25*SUM(G3:G7) -> -3026273.9 | J30: =J$25*SUM(J3:J7) -> -685125 | K30: =K$25*SUM(K3:K7) -> -1024558.8 | L30: =L$25*SUM(L3:L7) -> -1341082.5 | M30: =M$25*SUM(M3:M7) -> -1463288.7 | N30: =N$25*SUM(N3:N7) -> -1596630.8
P31: Warehouse and Plant Depreciation | R31: =$Q$35*CONSTANTS!$B$5 -> -30000 | S31: =$Q$35*CONSTANTS!$B$5 -> -30000 | T31: =$Q$35*CONSTANTS!$B$5 -> -30000 | U31: =$Q$35*CONSTANTS!$B$5 -> -30000 | V31: =$Q$35*CONSTANTS!$B$5 -> -30000
P32: Equipment | Q32: -300000 | R32: -300000 | S32: -300000 | T32: -300000 | U32: -300000 | V32: -300000
P33: Equipment Depreciation | R33: =$Q$32*CONSTANTS!$B$4 -> -37500 | S33: =$Q$32*CONSTANTS!$B$4*2 -> -75000 | T33: =$Q$32*CONSTANTS!$B$4*3 -> -112500 | U33: =$Q$32*CONSTANTS!$B$4*4 -> -150000 | V33: =$Q$32*CONSTANTS!$B$4*5 -> -187500
P34: Equipment Book Value | W34: =-(SUM(Q32:V32)-SUM(R33:V33)) -> 1237500
P35: Warehouse and plant | Q35: -750000 | W35: 880000
P36: Opportunity Cost(Rent) | R36: =-CONSTANTS!$B$6*12 -> -30000 | S36: =-CONSTANTS!$B$6*12 -> -30000 | T36: =-CONSTANTS!$B$6*12 -> -30000 | U36: =-CONSTANTS!$B$6*12 -> -30000 | V36: =-CONSTANTS!$B$6*12 -> -30000
A37: Estimated NWC | B37: =ABS(Wrangling!B30*CONSTANTS!$B$10)+ABS(CONSTANTS!$B$11*Wrangling!B22)-ABS(Wrangling!B30*CONSTANTS!$B$12) -> 0 | C37: =ABS(Wrangling!C30*CONSTANTS!$B$10)+ABS(CONSTANTS!$B$11*Wrangling!C22)-ABS(Wrangling!C30*CONSTANTS!$B$12) -> 464863 | D37: =ABS(Wrangling!D30*CONSTANTS!$B$10)+ABS(CONSTANTS!$B$11*Wrangling!D22)-ABS(Wrangling!D30*CONSTANTS!$B$12) -> 641187.05 | E37: =ABS(Wrangling!E30*CONSTANTS!$B$10)+ABS(CONSTANTS!$B$11*Wrangling!E22)-ABS(Wrangling!E30*CONSTANTS!$B$12) -> 870626.55 | F37: =ABS(Wrangling!F30*CONSTANTS!$B$10)+ABS(CONSTANTS!$B$11*Wrangling!F22)-ABS(Wrangling!F30*CONSTANTS!$B$12) -> 954969.96 | G37: =ABS(Wrangling!G30*CONSTANTS!$B$10)+ABS(CONSTANTS!$B$11*Wrangling!G22)-ABS(Wrangling!G30*CONSTANTS!$B$12) -> 1047636.7 | I37: 0 | J37: =ABS(Wrangling!J30*CONSTANTS!$B$10)+ABS(CONSTANTS!$B$11*Wrangling!J22)-ABS(Wrangling!J30*CONSTANTS!$B$12) -> 223256.25 | K37: =ABS(Wrangling!K30*CONSTANTS!$B$10)+ABS(CONSTANTS!$B$11*Wrangling!K22)-ABS(Wrangling!K30*CONSTANTS!$B$12) -> 343610.94 | L37: =ABS(Wrangling!L30*CONSTANTS!$B$10)+ABS(CONSTANTS!$B$11*Wrangling!L22)-ABS(Wrangling!L30*CONSTANTS!$B$12) -> 462961.88 | M37: =ABS(Wrangling!M30*CONSTANTS!$B$10)+ABS(CONSTANTS!$B$11*Wrangling!M22)-ABS(Wrangling!M30*CONSTANTS!$B$12) -> 520045.31 | N37: =ABS(Wrangling!N30*CONSTANTS!$B$10)+ABS(CONSTANTS!$B$11*Wrangling!N22)-ABS(Wrangling!N30*CONSTANTS!$B$12) -> 584248.33
P38: Salvage, NWC Recovery | W38: =SUM(W34:W35)+G37+N37 -> 3749385
A39: Delta NWC | B39: 0 | C39: =C37-B37 -> 464863 | D39: =D37-C37 -> 176324.05 | E39: =E37-D37 -> 229439.5 | F39: =F37-E37 -> 84343.408 | G39: =G37-F37 -> 92666.707 | I39: 0 | J39: =J37-I37 -> 223256.25 | K39: =K37-J37 -> 120354.69 | L39: =L37-K37 -> 119350.94 | M39: =M37-L37 -> 57083.43 | N39: =N37-M37 -> 64203.021
A41: Inventory | C41: =ABS(CONSTANTS!$B10*Wrangling!C$30) -> 150626 | D41: =ABS(CONSTANTS!$B10*Wrangling!D$30) -> 201924.1 | E41: =ABS(CONSTANTS!$B10*Wrangling!E$30) -> 266438.85 | F41: =ABS(CONSTANTS!$B10*Wrangling!F$30) -> 283957.2 | G41: =ABS(CONSTANTS!$B10*Wrangling!G$30) -> 302627.39 | J41: =ABS(CONSTANTS!$B10*Wrangling!J$30) -> 68512.5 | K41: =ABS(CONSTANTS!$B10*Wrangling!K$30) -> 102455.88 | L41: =ABS(CONSTANTS!$B10*Wrangling!L$30) -> 134108.25 | M41: =ABS(CONSTANTS!$B10*Wrangling!M$30) -> 146328.87 | N41: =ABS(CONSTANTS!$B10*Wrangling!N$30) -> 159663.08
A42: Receivables | C42: =CONSTANTS!$B11*C$22 -> 389550 | D42: =CONSTANTS!$B11*D$22 -> 540225 | E42: =CONSTANTS!$B11*E$22 -> 737407.13 | F42: =CONSTANTS!$B11*F$22 -> 812991.36 | G42: =CONSTANTS!$B11*G$22 -> 896322.97 | J42: =CONSTANTS!$B11*J$22 -> 189000 | K42: =CONSTANTS!$B11*K$22 -> 292383 | L42: =CONSTANTS!$B11*L$22 -> 395907.75 | M42: =CONSTANTS!$B11*M$22 -> 446880.87 | N42: =CONSTANTS!$B11*N$22 -> 504416.79
A43: Payables | C43: =ABS(CONSTANTS!$B12*Wrangling!C$30) -> 75313 | D43: =ABS(CONSTANTS!$B12*Wrangling!D$30) -> 100962.05 | E43: =ABS(CONSTANTS!$B12*Wrangling!E$30) -> 133219.42 | F43: =ABS(CONSTANTS!$B12*Wrangling!F$30) -> 141978.6 | G43: =ABS(CONSTANTS!$B12*Wrangling!G$30) -> 151313.7 | J43: =ABS(CONSTANTS!$B12*Wrangling!J$30) -> 34256.25 | K43: =ABS(CONSTANTS!$B12*Wrangling!K$30) -> 51227.938 | L43: =ABS(CONSTANTS!$B12*Wrangling!L$30) -> 67054.126 | M43: =ABS(CONSTANTS!$B12*Wrangling!M$30) -> 73164.433 | N43: =ABS(CONSTANTS!$B12*Wrangling!N$30) -> 79831.542
